otf/__init__.py
otf/_ipy_utils.py
otf/analyze.py
otf/ast_utils.py
otf/compiler.py
otf/decorators.py
otf/local_scheduler.py
otf/pack/__init__.py
otf/pack/_bin_tools.py
otf/pack/base.py
otf/pack/bin.py
otf/pack/text.py
otf/pack/tree.py
otf/parser.py
otf/pretty.py
otf/runtime.py
otf/utils.py
otf-0.1.0a5.dist-info/LICENSE
otf-0.1.0a5.dist-info/WHEEL
otf-0.1.0a5.dist-info/METADATA
otf-0.1.0a5.dist-info/RECORD
