Metadata-Version: 2.1
Name: otf
Version: 0.1.0a5
Summary: A python framework for on-the-fly distributed workflows
Home-page: https://github.com/till-varoquaux/otf
License: CC0-1.0
Author: Till Varoquaux
Author-email: till.varoquaux@gmail.com
Requires-Python: >=3.10,<4.0
Classifier: Development Status :: 2 - Pre-Alpha
Classifier: Intended Audience :: Developers
Classifier: Intended Audience :: Science/Research
Classifier: License :: CC0 1.0 Universal (CC0 1.0) Public Domain Dedication
Classifier: Programming Language :: Python
Classifier: Programming Language :: Python :: 3
Classifier: Programming Language :: Python :: 3.10
Classifier: Topic :: Software Development :: Libraries :: Application Frameworks
Provides-Extra: msgpack
Requires-Dist: msgpack (>=1.0.2,<2.0.0); extra == "msgpack"
Project-URL: Repository, https://github.com/till-varoquaux/otf
